mwparserfromhtml/__init__.py
mwparserfromhtml/dump/__init__.py
mwparserfromhtml/dump/dump.py
mwparserfromhtml/parse/__init__.py
mwparserfromhtml/parse/article.py
mwparserfromhtml/parse/const.py
mwparserfromhtml/parse/elements.py
mwparserfromhtml/parse/plaintext.py
mwparserfromhtml/parse/utils.py
mwparserfromhtml-2.0.3.dist-info/LICENSE
mwparserfromhtml-2.0.3.dist-info/METADATA
mwparserfromhtml-2.0.3.dist-info/WHEEL
mwparserfromhtml-2.0.3.dist-info/top_level.txt
mwparserfromhtml-2.0.3.dist-info/RECORD
